CHANGELOG.rst
CREDITS.rst
LICENSE.txt
MANIFEST.in
README.rst
pyproject.toml
requirements.txt
setup.py
licenses/ECLIPSE-ICONS-LICENSE.txt
packaging/icons/turAI-128x128.png
packaging/icons/turAI-16x16.png
packaging/icons/turAI-192x192.png
packaging/icons/turAI-2.png
packaging/icons/turAI-22x22.png
packaging/icons/turAI-256x256.png
packaging/icons/turAI-32x32.png
packaging/icons/turAI-48x48.png
packaging/icons/turAI-64x64.png
packaging/linux/org.turAI.turAI.appdata.xml
packaging/linux/org.turAI.turAI.desktop
packaging/linux/turAI.1
turAI/VERSION
turAI/__init__.py
turAI/__main__.py
turAI/assistance.py
turAI/ast_utils.py
turAI/backend.py
turAI/base_file_browser.py
turAI/codeview.py
turAI/common.py
turAI/config.py
turAI/config_ui.py
turAI/custom_notebook.py
turAI/defaults.ini
turAI/dnd.py
turAI/editor_helpers.py
turAI/editors.py
turAI/export.py
turAI/first_run.py
turAI/gridtable.py
turAI/jedi_utils.py
turAI/languages.py
turAI/memory.py
turAI/misc_utils.py
turAI/roughparse.py
turAI/rst_utils.py
turAI/running.py
turAI/shell.py
turAI/terminal.py
turAI/tktextext.py
turAI/token_utils.py
turAI/udisks.py
turAI/ui_utils.py
turAI/workbench.py
turAI/workdlg.py
turAI.egg-info/PKG-INFO
turAI.egg-info/SOURCES.txt
turAI.egg-info/dependency_links.txt
turAI.egg-info/entry_points.txt
turAI.egg-info/requires.txt
turAI.egg-info/top_level.txt
turAI/dbus/org.freedesktop.DBus.ObjectManager.xml
turAI/dbus/org.freedesktop.UDisks2.xml
turAI/locale/compile_mo.bat
turAI/locale/register_updates.py
turAI/locale/thonny.pot
turAI/locale/update_pot.bat
turAI/locale/ar_AR/LC_MESSAGES/thonny.mo
turAI/locale/ar_AR/LC_MESSAGES/thonny.po
turAI/locale/ca_ES/LC_MESSAGES/thonny.mo
turAI/locale/ca_ES/LC_MESSAGES/thonny.po
turAI/locale/cs_CZ/LC_MESSAGES/thonny.mo
turAI/locale/cs_CZ/LC_MESSAGES/thonny.po
turAI/locale/de_DE/LC_MESSAGES/thonny.mo
turAI/locale/de_DE/LC_MESSAGES/thonny.po
turAI/locale/el_GR/LC_MESSAGES/thonny.mo
turAI/locale/el_GR/LC_MESSAGES/thonny.po
turAI/locale/en_GB/LC_MESSAGES/thonny.mo
turAI/locale/en_GB/LC_MESSAGES/thonny.po
turAI/locale/en_US/LC_MESSAGES/thonny.mo
turAI/locale/en_US/LC_MESSAGES/thonny.po
turAI/locale/es_ES/HELP_CONTENT/debuggers.rst
