Metadata-Version: 2.1
Name: turAI
Version: 0.0.12
Summary: Python IDE for beginners
Home-page: https://turAI.org
Author: Aivar Annamaa and others
Author-email: turAI@googlegroups.com
License: MIT
Project-URL: Source code, https://github.com/turAI/turAI
Project-URL: Bug tracker, https://github.com/turAI/turAI/issues
Keywords: IDE education debugger
Platform: Windows
Platform: macOS
Platform: Linux
Classifier: Development Status :: 5 - Production/Stable
Classifier: Environment :: MacOS X
Classifier: Environment :: Win32 (MS Windows)
Classifier: Environment :: X11 Applications
Classifier: Intended Audience :: Developers
Classifier: Intended Audience :: Education
Classifier: Intended Audience :: End Users/Desktop
Classifier: License :: Freeware
Classifier: License :: OSI Approved :: MIT License
Classifier: Natural Language :: English
Classifier: Operating System :: MacOS
Classifier: Operating System :: Microsoft :: Windows
Classifier: Operating System :: POSIX
Classifier: Operating System :: POSIX :: Linux
Classifier: Programming Language :: Python
Classifier: Programming Language :: Python :: 3
Classifier: Programming Language :: Python :: 3 :: Only
Classifier: Programming Language :: Python :: 3.8
Classifier: Programming Language :: Python :: 3.9
Classifier: Programming Language :: Python :: 3.10
Classifier: Programming Language :: Python :: 3.11
Classifier: Programming Language :: Python :: 3.12
Classifier: Topic :: Education
Classifier: Topic :: Software Development
Classifier: Topic :: Software Development :: Debuggers
Classifier: Topic :: Text Editors
Requires-Python: >=3.8
License-File: LICENSE.txt
Requires-Dist: jedi>=0.18.1
Requires-Dist: setuptools>=45.2
Requires-Dist: pyserial>=3.4
Requires-Dist: pylint>=2.4
Requires-Dist: docutils>=0.16
Requires-Dist: mypy>=0.761
Requires-Dist: asttokens>=2.0
Requires-Dist: Send2Trash>=1.5
Requires-Dist: wheel
